[
  {
    "symbol": "RELIANCE",
    "price": 1497.0,
    "previous_close": 1489.3,
    "price_change_pct": 0.52,
    "price_direction": "\u2191",
    "total_ce_oi": 0,
    "total_pe_oi": 0,
    "oi_change_pct": -100.0,
    "ce_oi_change_pct": -100.0,
    "pe_oi_change_pct": -100.0,
    "oi_direction": "\u2193",
    "pcr": 0,
    "sentiment": "Bullish",
    "signal": "Short Covering \u26a0\ufe0f",
    "build_side": "Balanced",
    "conflict": true,
    "timestamp": "2025-11-11 09:15:04"
  },
  {
    "symbol": "TCS",
    "price": 3045.0,
    "previous_close": 3025.2,
    "price_change_pct": 0.65,
    "price_direction": "\u2191",
    "total_ce_oi": 79138,
    "total_pe_oi": 53906,
    "oi_change_pct": -0.34,
    "ce_oi_change_pct": -0.76,
    "pe_oi_change_pct": 0.28,
    "oi_direction": "\u2193",
    "pcr": 0.68,
    "sentiment": "Bullish",
    "signal": "Short Covering \u26a0\ufe0f",
    "build_side": "Put Side",
    "conflict": true,
    "timestamp": "2025-11-11 09:15:04"
  },
  {
    "symbol": "INFY",
    "price": 1525.0,
    "previous_close": 1513.5,
    "price_change_pct": 0.76,
    "price_direction": "\u2191",
    "total_ce_oi": 0,
    "total_pe_oi": 0,
    "oi_change_pct": -100.0,
    "ce_oi_change_pct": -100.0,
    "pe_oi_change_pct": -100.0,
    "oi_direction": "\u2193",
    "pcr": 0,
    "sentiment": "Bullish",
    "signal": "Short Covering \u26a0\ufe0f",
    "build_side": "Balanced",
    "conflict": true,
    "timestamp": "2025-11-11 09:15:05"
  },
  {
    "symbol": "HDFCBANK",
    "price": 983.5,
    "previous_close": 984.5,
    "price_change_pct": -0.1,
    "price_direction": "\u2193",
    "total_ce_oi": 61834,
    "total_pe_oi": 39063,
    "oi_change_pct": -8.81,
    "ce_oi_change_pct": -5.28,
    "pe_oi_change_pct": -13.88,
    "oi_direction": "\u2193",
    "pcr": 0.63,
    "sentiment": "Bullish",
    "signal": "Long Unwinding",
    "build_side": "Call Side",
    "conflict": false,
    "timestamp": "2025-11-11 09:15:06"
  },
  {
    "symbol": "LT",
    "price": 3929.0,
    "previous_close": 3918.5,
    "price_change_pct": 0.27,
    "price_direction": "\u2191",
    "total_ce_oi": 40349,
    "total_pe_oi": 20405,
    "oi_change_pct": -0.13,
    "ce_oi_change_pct": -0.25,
    "pe_oi_change_pct": 0.11,
    "oi_direction": "\u2193",
    "pcr": 0.51,
    "sentiment": "Bullish",
    "signal": "Short Covering \u26a0\ufe0f",
    "build_side": "Balanced",
    "conflict": true,
    "timestamp": "2025-11-11 09:15:06"
  },
  {
    "symbol": "ITC",
    "price": 406.0,
    "previous_close": 405.55,
    "price_change_pct": 0.11,
    "price_direction": "\u2191",
    "total_ce_oi": 4943,
    "total_pe_oi": 721,
    "oi_change_pct": -90.22,
    "ce_oi_change_pct": -87.14,
    "pe_oi_change_pct": -96.3,
    "oi_direction": "\u2193",
    "pcr": 0.15,
    "sentiment": "Bullish",
    "signal": "Short Covering \u26a0\ufe0f",
    "build_side": "Call Side",
    "conflict": true,
    "timestamp": "2025-11-11 09:15:07"
  },
  {
    "symbol": "SBIN",
    "price": 953.6,
    "previous_close": 951.15,
    "price_change_pct": 0.26,
    "price_direction": "\u2191",
    "total_ce_oi": 24341,
    "total_pe_oi": 31491,
    "oi_change_pct": -50.03,
    "ce_oi_change_pct": -61.65,
    "pe_oi_change_pct": -34.74,
    "oi_direction": "\u2193",
    "pcr": 1.29,
    "sentiment": "Bearish",
    "signal": "Short Covering",
    "build_side": "Put Side",
    "conflict": false,
    "timestamp": "2025-11-11 09:15:08"
  },
  {
    "symbol": "AXISBANK",
    "price": 1218.1,
    "previous_close": 1217.0,
    "price_change_pct": 0.09,
    "price_direction": "\u2191",
    "total_ce_oi": 0,
    "total_pe_oi": 0,
    "oi_change_pct": -100.0,
    "ce_oi_change_pct": -100.0,
    "pe_oi_change_pct": -100.0,
    "oi_direction": "\u2193",
    "pcr": 0,
    "sentiment": "Bullish",
    "signal": "Short Covering \u26a0\ufe0f",
    "build_side": "Balanced",
    "conflict": true,
    "timestamp": "2025-11-11 09:15:08"
  },
  {
    "symbol": "KOTAKBANK",
    "price": 2100.0,
    "previous_close": 2092.7,
    "price_change_pct": 0.35,
    "price_direction": "\u2191",
    "total_ce_oi": 0,
    "total_pe_oi": 0,
    "oi_change_pct": -100.0,
    "ce_oi_change_pct": -100.0,
    "pe_oi_change_pct": -100.0,
    "oi_direction": "\u2193",
    "pcr": 0,
    "sentiment": "Bullish",
    "signal": "Short Covering \u26a0\ufe0f",
    "build_side": "Balanced",
    "conflict": true,
    "timestamp": "2025-11-11 09:15:09"
  },
  {
    "symbol": "BHARTIARTL",
    "price": 2020.1,
    "previous_close": 2019.8,
    "price_change_pct": 0.01,
    "price_direction": "\u2191",
    "total_ce_oi": 24,
    "total_pe_oi": 7654,
    "oi_change_pct": -90.36,
    "ce_oi_change_pct": -99.96,
    "pe_oi_change_pct": -61.72,
    "oi_direction": "\u2193",
    "pcr": 318.92,
    "sentiment": "Bearish",
    "signal": "Short Covering",
    "build_side": "Put Side",
    "conflict": false,
    "timestamp": "2025-11-11 09:15:10"
  },
  {
    "symbol": "SUNPHARMA",
    "price": 1701.6,
    "previous_close": 1697.8,
    "price_change_pct": 0.22,
    "price_direction": "\u2191",
    "total_ce_oi": 142,
    "total_pe_oi": 6278,
    "oi_change_pct": -65.83,
    "ce_oi_change_pct": -98.84,
    "pe_oi_change_pct": -3.58,
    "oi_direction": "\u2193",
    "pcr": 44.21,
    "sentiment": "Bearish",
    "signal": "Short Covering",
    "build_side": "Put Side",
    "conflict": false,
    "timestamp": "2025-11-11 09:15:10"
  },
  {
    "symbol": "ONGC",
    "price": 254.2,
    "previous_close": 251.4,
    "price_change_pct": 1.11,
    "price_direction": "\u2191",
    "total_ce_oi": 22093,
    "total_pe_oi": 8637,
    "oi_change_pct": 2.05,
    "ce_oi_change_pct": 0.89,
    "pe_oi_change_pct": 5.14,
    "oi_direction": "\u2191",
    "pcr": 0.39,
    "sentiment": "Bullish",
    "signal": "Long Build-up",
    "build_side": "Put Side",
    "conflict": false,
    "timestamp": "2025-11-11 09:15:12"
  },
  {
    "symbol": "BAJAJFINSV",
    "price": 2085.0,
    "previous_close": 2118.3,
    "price_change_pct": -1.57,
    "price_direction": "\u2193",
    "total_ce_oi": 0,
    "total_pe_oi": 0,
    "oi_change_pct": -100.0,
    "ce_oi_change_pct": -100.0,
    "pe_oi_change_pct": -100.0,
    "oi_direction": "\u2193",
    "pcr": 0,
    "sentiment": "Bullish",
    "signal": "Long Unwinding",
    "build_side": "Balanced",
    "conflict": false,
    "timestamp": "2025-11-11 09:15:13"
  },
  {
    "symbol": "ADANIENT",
    "price": 2370.3,
    "previous_close": 2370.7,
    "price_change_pct": -0.02,
    "price_direction": "\u2193",
    "total_ce_oi": 0,
    "total_pe_oi": 0,
    "oi_change_pct": -100.0,
    "ce_oi_change_pct": -100.0,
    "pe_oi_change_pct": -100.0,
    "oi_direction": "\u2193",
    "pcr": 0,
    "sentiment": "Bullish",
    "signal": "Long Unwinding",
    "build_side": "Balanced",
    "conflict": false,
    "timestamp": "2025-11-11 09:15:15"
  },
  {
    "symbol": "M&M",
    "price": 3699.9,
    "previous_close": 3663.9,
    "price_change_pct": 0.98,
    "price_direction": "\u2191",
    "total_ce_oi": 0,
    "total_pe_oi": 0,
    "oi_change_pct": -100.0,
    "ce_oi_change_pct": -100.0,
    "pe_oi_change_pct": -100.0,
    "oi_direction": "\u2193",
    "pcr": 0,
    "sentiment": "Bullish",
    "signal": "Short Covering \u26a0\ufe0f",
    "build_side": "Balanced",
    "conflict": true,
    "timestamp": "2025-11-11 09:15:16"
  },
  {
    "symbol": "COALINDIA",
    "price": 382.5,
    "previous_close": 381.35,
    "price_change_pct": 0.3,
    "price_direction": "\u2191",
    "total_ce_oi": 0,
    "total_pe_oi": 0,
    "oi_change_pct": -100.0,
    "ce_oi_change_pct": -100.0,
    "pe_oi_change_pct": -100.0,
    "oi_direction": "\u2193",
    "pcr": 0,
    "sentiment": "Bullish",
    "signal": "Short Covering \u26a0\ufe0f",
    "build_side": "Balanced",
    "conflict": true,
    "timestamp": "2025-11-11 09:15:17"
  },
  {
    "symbol": "JIOFIN",
    "price": 302.0,
    "previous_close": 301.95,
    "price_change_pct": 0.02,
    "price_direction": "\u2191",
    "total_ce_oi": 0,
    "total_pe_oi": 0,
    "oi_change_pct": -100.0,
    "ce_oi_change_pct": -100.0,
    "pe_oi_change_pct": -100.0,
    "oi_direction": "\u2193",
    "pcr": 0,
    "sentiment": "Bullish",
    "signal": "Short Covering \u26a0\ufe0f",
    "build_side": "Balanced",
    "conflict": true,
    "timestamp": "2025-11-11 09:15:17"
  },
  {
    "symbol": "IDFCFIRSTB",
    "price": 81.33,
    "previous_close": 81.21,
    "price_change_pct": 0.15,
    "price_direction": "\u2191",
    "total_ce_oi": 0,
    "total_pe_oi": 0,
    "oi_change_pct": -100.0,
    "ce_oi_change_pct": -100.0,
    "pe_oi_change_pct": -100.0,
    "oi_direction": "\u2193",
    "pcr": 0,
    "sentiment": "Bullish",
    "signal": "Short Covering \u26a0\ufe0f",
    "build_side": "Balanced",
    "conflict": true,
    "timestamp": "2025-11-11 09:15:18"
  },
  {
    "symbol": "DRREDDY",
    "price": 1204.4,
    "previous_close": 1198.7,
    "price_change_pct": 0.48,
    "price_direction": "\u2191",
    "total_ce_oi": 0,
    "total_pe_oi": 0,
    "oi_change_pct": -100.0,
    "ce_oi_change_pct": -100.0,
    "pe_oi_change_pct": -100.0,
    "oi_direction": "\u2193",
    "pcr": 0,
    "sentiment": "Bullish",
    "signal": "Short Covering \u26a0\ufe0f",
    "build_side": "Balanced",
    "conflict": true,
    "timestamp": "2025-11-11 09:15:19"
  }
]