[
  {
    "symbol": "RELIANCE",
    "price": 1412.5,
    "previous_close": 1393.7,
    "price_change_pct": 1.35,
    "price_direction": "\u2191",
    "total_ce_oi": 91202,
    "total_pe_oi": 58382,
    "oi_change_pct": -0.08,
    "ce_oi_change_pct": -0.07,
    "pe_oi_change_pct": -0.09,
    "oi_direction": "\u2193",
    "pcr": 0.64,
    "sentiment": "Bullish",
    "signal": "Short Covering \u26a0\ufe0f",
    "build_side": "Balanced",
    "conflict": true
  },
  {
    "symbol": "TCS",
    "price": 3014.3,
    "previous_close": 3003.0,
    "price_change_pct": 0.38,
    "price_direction": "\u2191",
    "total_ce_oi": 84910,
    "total_pe_oi": 57972,
    "oi_change_pct": 0.19,
    "ce_oi_change_pct": 0.28,
    "pe_oi_change_pct": 0.06,
    "oi_direction": "\u2191",
    "pcr": 0.68,
    "sentiment": "Bullish",
    "signal": "Long Build-up",
    "build_side": "Balanced",
    "conflict": false
  },
  {
    "symbol": "INFY",
    "price": 1462.0,
    "previous_close": 1469.6,
    "price_change_pct": -0.52,
    "price_direction": "\u2193",
    "total_ce_oi": 40817,
    "total_pe_oi": 21487,
    "oi_change_pct": 0.25,
    "ce_oi_change_pct": 0.33,
    "pe_oi_change_pct": 0.08,
    "oi_direction": "\u2191",
    "pcr": 0.53,
    "sentiment": "Bullish",
    "signal": "Short Build-up \u26a0\ufe0f",
    "build_side": "Balanced",
    "conflict": true
  },
  {
    "symbol": "HDFCBANK",
    "price": 2004.7,
    "previous_close": 2012.2,
    "price_change_pct": -0.37,
    "price_direction": "\u2193",
    "total_ce_oi": 24852,
    "total_pe_oi": 23731,
    "oi_change_pct": 0.64,
    "ce_oi_change_pct": 1.43,
    "pe_oi_change_pct": -0.18,
    "oi_direction": "\u2191",
    "pcr": 0.95,
    "sentiment": "Neutral",
    "signal": "Short Build-up",
    "build_side": "Call Side",
    "conflict": false
  },
  {
    "symbol": "ICICIBANK",
    "price": 1469.1,
    "previous_close": 1471.6,
    "price_change_pct": -0.17,
    "price_direction": "\u2193",
    "total_ce_oi": 20601,
    "total_pe_oi": 14816,
    "oi_change_pct": 0.7,
    "ce_oi_change_pct": 1.18,
    "pe_oi_change_pct": 0.03,
    "oi_direction": "\u2191",
    "pcr": 0.72,
    "sentiment": "Bullish",
    "signal": "Short Build-up \u26a0\ufe0f",
    "build_side": "Call Side",
    "conflict": true
  },
  {
    "symbol": "LT",
    "price": 3614.6,
    "previous_close": 3587.3,
    "price_change_pct": 0.76,
    "price_direction": "\u2191",
    "total_ce_oi": 19428,
    "total_pe_oi": 13532,
    "oi_change_pct": -0.34,
    "ce_oi_change_pct": -0.69,
    "pe_oi_change_pct": 0.15,
    "oi_direction": "\u2193",
    "pcr": 0.7,
    "sentiment": "Bullish",
    "signal": "Short Covering \u26a0\ufe0f",
    "build_side": "Balanced",
    "conflict": true
  },
  {
    "symbol": "ITC",
    "price": 418.05,
    "previous_close": 416.45,
    "price_change_pct": 0.38,
    "price_direction": "\u2191",
    "total_ce_oi": 30547,
    "total_pe_oi": 15983,
    "oi_change_pct": 0.01,
    "ce_oi_change_pct": -0.08,
    "pe_oi_change_pct": 0.17,
    "oi_direction": "\u2191",
    "pcr": 0.52,
    "sentiment": "Bullish",
    "signal": "Long Build-up",
    "build_side": "Balanced",
    "conflict": false
  },
  {
    "symbol": "SBIN",
    "price": 788.85,
    "previous_close": 794.0,
    "price_change_pct": -0.65,
    "price_direction": "\u2193",
    "total_ce_oi": 55458,
    "total_pe_oi": 43489,
    "oi_change_pct": 0.58,
    "ce_oi_change_pct": 0.8,
    "pe_oi_change_pct": 0.31,
    "oi_direction": "\u2191",
    "pcr": 0.78,
    "sentiment": "Bullish",
    "signal": "Short Build-up \u26a0\ufe0f",
    "build_side": "Balanced",
    "conflict": true
  },
  {
    "symbol": "AXISBANK",
    "price": 1065.9,
    "previous_close": 1062.4,
    "price_change_pct": 0.33,
    "price_direction": "\u2191",
    "total_ce_oi": 26372,
    "total_pe_oi": 16832,
    "oi_change_pct": 0.13,
    "ce_oi_change_pct": 0.19,
    "pe_oi_change_pct": 0.04,
    "oi_direction": "\u2191",
    "pcr": 0.64,
    "sentiment": "Bullish",
    "signal": "Long Build-up",
    "build_side": "Balanced",
    "conflict": false
  },
  {
    "symbol": "KOTAKBANK",
    "price": 1992.0,
    "previous_close": 1992.4,
    "price_change_pct": -0.02,
    "price_direction": "\u2193",
    "total_ce_oi": 18352,
    "total_pe_oi": 12619,
    "oi_change_pct": -0.13,
    "ce_oi_change_pct": -0.07,
    "pe_oi_change_pct": -0.21,
    "oi_direction": "\u2193",
    "pcr": 0.69,
    "sentiment": "Bullish",
    "signal": "Long Unwinding",
    "build_side": "Balanced",
    "conflict": false
  },
  {
    "symbol": "BHARTIARTL",
    "price": 1892.9,
    "previous_close": 1884.4,
    "price_change_pct": 0.45,
    "price_direction": "\u2191",
    "total_ce_oi": 15456,
    "total_pe_oi": 8960,
    "oi_change_pct": 0.55,
    "ce_oi_change_pct": 0.79,
    "pe_oi_change_pct": 0.13,
    "oi_direction": "\u2191",
    "pcr": 0.58,
    "sentiment": "Bullish",
    "signal": "Long Build-up",
    "build_side": "Balanced",
    "conflict": false
  },
  {
    "symbol": "BAJFINANCE",
    "price": 881.8,
    "previous_close": 875.6,
    "price_change_pct": 0.71,
    "price_direction": "\u2191",
    "total_ce_oi": 27326,
    "total_pe_oi": 14417,
    "oi_change_pct": -0.11,
    "ce_oi_change_pct": -0.14,
    "pe_oi_change_pct": -0.03,
    "oi_direction": "\u2193",
    "pcr": 0.53,
    "sentiment": "Bullish",
    "signal": "Short Covering \u26a0\ufe0f",
    "build_side": "Balanced",
    "conflict": true
  },
  {
    "symbol": "SUNPHARMA",
    "price": 1630.9,
    "previous_close": 1629.7,
    "price_change_pct": 0.07,
    "price_direction": "\u2191",
    "total_ce_oi": 18839,
    "total_pe_oi": 11534,
    "oi_change_pct": -0.2,
    "ce_oi_change_pct": -0.32,
    "pe_oi_change_pct": -0.01,
    "oi_direction": "\u2193",
    "pcr": 0.61,
    "sentiment": "Bullish",
    "signal": "Short Covering \u26a0\ufe0f",
    "build_side": "Balanced",
    "conflict": true
  },
  {
    "symbol": "TECHM",
    "price": 1436.1,
    "previous_close": 1438.8,
    "price_change_pct": -0.19,
    "price_direction": "\u2193",
    "total_ce_oi": 8587,
    "total_pe_oi": 5464,
    "oi_change_pct": -0.04,
    "ce_oi_change_pct": 0.05,
    "pe_oi_change_pct": -0.16,
    "oi_direction": "\u2193",
    "pcr": 0.64,
    "sentiment": "Bullish",
    "signal": "Long Unwinding",
    "build_side": "Balanced",
    "conflict": false
  },
  {
    "symbol": "NTPC",
    "price": 327.95,
    "previous_close": 330.9,
    "price_change_pct": -0.89,
    "price_direction": "\u2193",
    "total_ce_oi": 15930,
    "total_pe_oi": 7549,
    "oi_change_pct": 1.94,
    "ce_oi_change_pct": 2.44,
    "pe_oi_change_pct": 0.88,
    "oi_direction": "\u2191",
    "pcr": 0.47,
    "sentiment": "Bullish",
    "signal": "Short Build-up \u26a0\ufe0f",
    "build_side": "Call Side",
    "conflict": true
  },
  {
    "symbol": "ONGC",
    "price": 234.86,
    "previous_close": 236.79,
    "price_change_pct": -0.82,
    "price_direction": "\u2193",
    "total_ce_oi": 10336,
    "total_pe_oi": 6554,
    "oi_change_pct": 2.93,
    "ce_oi_change_pct": 4.41,
    "pe_oi_change_pct": 0.68,
    "oi_direction": "\u2191",
    "pcr": 0.63,
    "sentiment": "Bullish",
    "signal": "Short Build-up \u26a0\ufe0f",
    "build_side": "Call Side",
    "conflict": true
  },
  {
    "symbol": "TATAMOTORS",
    "price": 653.7,
    "previous_close": 648.85,
    "price_change_pct": 0.75,
    "price_direction": "\u2191",
    "total_ce_oi": 33660,
    "total_pe_oi": 26396,
    "oi_change_pct": 0.12,
    "ce_oi_change_pct": 0.06,
    "pe_oi_change_pct": 0.19,
    "oi_direction": "\u2191",
    "pcr": 0.78,
    "sentiment": "Bullish",
    "signal": "Long Build-up",
    "build_side": "Balanced",
    "conflict": false
  },
  {
    "symbol": "BAJAJFINSV",
    "price": 1938.0,
    "previous_close": 1916.3,
    "price_change_pct": 1.13,
    "price_direction": "\u2191",
    "total_ce_oi": 9342,
    "total_pe_oi": 5750,
    "oi_change_pct": -0.51,
    "ce_oi_change_pct": -1.05,
    "pe_oi_change_pct": 0.38,
    "oi_direction": "\u2193",
    "pcr": 0.62,
    "sentiment": "Bullish",
    "signal": "Short Covering \u26a0\ufe0f",
    "build_side": "Put Side",
    "conflict": true
  },
  {
    "symbol": "HDFCLIFE",
    "price": 743.4,
    "previous_close": 741.7,
    "price_change_pct": 0.23,
    "price_direction": "\u2191",
    "total_ce_oi": 4979,
    "total_pe_oi": 3241,
    "oi_change_pct": 0.27,
    "ce_oi_change_pct": 0.36,
    "pe_oi_change_pct": 0.12,
    "oi_direction": "\u2191",
    "pcr": 0.65,
    "sentiment": "Bullish",
    "signal": "Long Build-up",
    "build_side": "Balanced",
    "conflict": false
  },
  {
    "symbol": "ADANIENT",
    "price": 2356.0,
    "previous_close": 2350.9,
    "price_change_pct": 0.22,
    "price_direction": "\u2191",
    "total_ce_oi": 21389,
    "total_pe_oi": 19249,
    "oi_change_pct": 0.03,
    "ce_oi_change_pct": 0.01,
    "pe_oi_change_pct": 0.05,
    "oi_direction": "\u2191",
    "pcr": 0.9,
    "sentiment": "Neutral",
    "signal": "Long Build-up",
    "build_side": "Balanced",
    "conflict": false
  },
  {
    "symbol": "DIVISLAB",
    "price": 6403.0,
    "previous_close": 6361.5,
    "price_change_pct": 0.65,
    "price_direction": "\u2191",
    "total_ce_oi": 6116,
    "total_pe_oi": 4584,
    "oi_change_pct": 2.2,
    "ce_oi_change_pct": 3.91,
    "pe_oi_change_pct": 0.0,
    "oi_direction": "\u2191",
    "pcr": 0.75,
    "sentiment": "Bullish",
    "signal": "Long Build-up",
    "build_side": "Call Side",
    "conflict": false
  },
  {
    "symbol": "EICHERMOT",
    "price": 5585.0,
    "previous_close": 5528.0,
    "price_change_pct": 1.03,
    "price_direction": "\u2191",
    "total_ce_oi": 7943,
    "total_pe_oi": 4623,
    "oi_change_pct": 0.54,
    "ce_oi_change_pct": 0.74,
    "pe_oi_change_pct": 0.2,
    "oi_direction": "\u2191",
    "pcr": 0.58,
    "sentiment": "Bullish",
    "signal": "Long Build-up",
    "build_side": "Balanced",
    "conflict": false
  },
  {
    "symbol": "M&M",
    "price": 3202.4,
    "previous_close": 3159.3,
    "price_change_pct": 1.36,
    "price_direction": "\u2191",
    "total_ce_oi": 20516,
    "total_pe_oi": 12681,
    "oi_change_pct": 0.51,
    "ce_oi_change_pct": 0.47,
    "pe_oi_change_pct": 0.57,
    "oi_direction": "\u2191",
    "pcr": 0.62,
    "sentiment": "Bullish",
    "signal": "Long Build-up",
    "build_side": "Balanced",
    "conflict": false
  },
  {
    "symbol": "COALINDIA",
    "price": 375.35,
    "previous_close": 372.5,
    "price_change_pct": 0.77,
    "price_direction": "\u2191",
    "total_ce_oi": 21122,
    "total_pe_oi": 17293,
    "oi_change_pct": -0.09,
    "ce_oi_change_pct": -0.25,
    "pe_oi_change_pct": 0.1,
    "oi_direction": "\u2193",
    "pcr": 0.82,
    "sentiment": "Neutral",
    "signal": "Short Covering",
    "build_side": "Balanced",
    "conflict": false
  },
  {
    "symbol": "JIOFIN",
    "price": 331.8,
    "previous_close": 329.5,
    "price_change_pct": 0.7,
    "price_direction": "\u2191",
    "total_ce_oi": 19386,
    "total_pe_oi": 15033,
    "oi_change_pct": -0.07,
    "ce_oi_change_pct": 0.39,
    "pe_oi_change_pct": -0.66,
    "oi_direction": "\u2193",
    "pcr": 0.78,
    "sentiment": "Bullish",
    "signal": "Short Covering \u26a0\ufe0f",
    "build_side": "Call Side",
    "conflict": true
  }
]