[
  {
    "symbol": "RELIANCE",
    "price": 1363.2,
    "previous_close": 1368.7,
    "price_change_pct": -0.4,
    "price_direction": "\u2193",
    "total_ce_oi": 75389,
    "total_pe_oi": 58866,
    "oi_change_pct": 1.83,
    "ce_oi_change_pct": 2.19,
    "pe_oi_change_pct": 1.38,
    "oi_direction": "\u2191",
    "pcr": 0.78,
    "sentiment": "Bullish",
    "signal": "Short Build-up \u26a0\ufe0f",
    "build_side": "Balanced",
    "conflict": true,
    "timestamp": "2025-10-03 10:00:04"
  },
  {
    "symbol": "TCS",
    "price": 2914.0,
    "previous_close": 2914.2,
    "price_change_pct": -0.01,
    "price_direction": "\u2193",
    "total_ce_oi": 70638,
    "total_pe_oi": 56888,
    "oi_change_pct": 0.33,
    "ce_oi_change_pct": 0.36,
    "pe_oi_change_pct": 0.3,
    "oi_direction": "\u2191",
    "pcr": 0.81,
    "sentiment": "Neutral",
    "signal": "Short Build-up",
    "build_side": "Balanced",
    "conflict": false,
    "timestamp": "2025-10-03 10:00:04"
  },
  {
    "symbol": "INFY",
    "price": 1442.7,
    "previous_close": 1445.8,
    "price_change_pct": -0.21,
    "price_direction": "\u2193",
    "total_ce_oi": 40670,
    "total_pe_oi": 36130,
    "oi_change_pct": 0.62,
    "ce_oi_change_pct": 0.8,
    "pe_oi_change_pct": 0.43,
    "oi_direction": "\u2191",
    "pcr": 0.89,
    "sentiment": "Neutral",
    "signal": "Short Build-up",
    "build_side": "Balanced",
    "conflict": false,
    "timestamp": "2025-10-03 10:00:05"
  },
  {
    "symbol": "HDFCBANK",
    "price": 959.05,
    "previous_close": 965.25,
    "price_change_pct": -0.64,
    "price_direction": "\u2193",
    "total_ce_oi": 25946,
    "total_pe_oi": 20089,
    "oi_change_pct": 1.73,
    "ce_oi_change_pct": 2.0,
    "pe_oi_change_pct": 1.39,
    "oi_direction": "\u2191",
    "pcr": 0.77,
    "sentiment": "Bullish",
    "signal": "Short Build-up \u26a0\ufe0f",
    "build_side": "Balanced",
    "conflict": true,
    "timestamp": "2025-10-03 10:00:06"
  },
  {
    "symbol": "ICICIBANK",
    "price": 1370.1,
    "previous_close": 1372.0,
    "price_change_pct": -0.14,
    "price_direction": "\u2193",
    "total_ce_oi": 23323,
    "total_pe_oi": 18611,
    "oi_change_pct": 1.12,
    "ce_oi_change_pct": 0.37,
    "pe_oi_change_pct": 2.07,
    "oi_direction": "\u2191",
    "pcr": 0.8,
    "sentiment": "Neutral",
    "signal": "Short Build-up",
    "build_side": "Put Side",
    "conflict": false,
    "timestamp": "2025-10-03 10:00:07"
  },
  {
    "symbol": "LT",
    "price": 3694.2,
    "previous_close": 3670.3,
    "price_change_pct": 0.65,
    "price_direction": "\u2191",
    "total_ce_oi": 24497,
    "total_pe_oi": 13531,
    "oi_change_pct": -0.42,
    "ce_oi_change_pct": -0.8,
    "pe_oi_change_pct": 0.28,
    "oi_direction": "\u2193",
    "pcr": 0.55,
    "sentiment": "Bullish",
    "signal": "Short Covering \u26a0\ufe0f",
    "build_side": "Put Side",
    "conflict": true,
    "timestamp": "2025-10-03 10:00:08"
  },
  {
    "symbol": "ITC",
    "price": 404.25,
    "previous_close": 405.6,
    "price_change_pct": -0.33,
    "price_direction": "\u2193",
    "total_ce_oi": 20187,
    "total_pe_oi": 14841,
    "oi_change_pct": 0.33,
    "ce_oi_change_pct": 0.22,
    "pe_oi_change_pct": 0.47,
    "oi_direction": "\u2191",
    "pcr": 0.74,
    "sentiment": "Bullish",
    "signal": "Short Build-up \u26a0\ufe0f",
    "build_side": "Balanced",
    "conflict": true,
    "timestamp": "2025-10-03 10:00:08"
  },
  {
    "symbol": "SBIN",
    "price": 871.95,
    "previous_close": 864.1,
    "price_change_pct": 0.91,
    "price_direction": "\u2191",
    "total_ce_oi": 46392,
    "total_pe_oi": 29577,
    "oi_change_pct": -0.4,
    "ce_oi_change_pct": -1.13,
    "pe_oi_change_pct": 0.76,
    "oi_direction": "\u2193",
    "pcr": 0.64,
    "sentiment": "Bullish",
    "signal": "Short Covering \u26a0\ufe0f",
    "build_side": "Put Side",
    "conflict": true,
    "timestamp": "2025-10-03 10:00:09"
  },
  {
    "symbol": "AXISBANK",
    "price": 1181.5,
    "previous_close": 1159.5,
    "price_change_pct": 1.9,
    "price_direction": "\u2191",
    "total_ce_oi": 35368,
    "total_pe_oi": 14490,
    "oi_change_pct": 1.44,
    "ce_oi_change_pct": 1.03,
    "pe_oi_change_pct": 2.44,
    "oi_direction": "\u2191",
    "pcr": 0.41,
    "sentiment": "Bullish",
    "signal": "Long Build-up",
    "build_side": "Put Side",
    "conflict": false,
    "timestamp": "2025-10-03 10:00:09"
  },
  {
    "symbol": "KOTAKBANK",
    "price": 2092.5,
    "previous_close": 2063.3,
    "price_change_pct": 1.42,
    "price_direction": "\u2191",
    "total_ce_oi": 15748,
    "total_pe_oi": 15490,
    "oi_change_pct": 5.87,
    "ce_oi_change_pct": 3.71,
    "pe_oi_change_pct": 8.15,
    "oi_direction": "\u2191",
    "pcr": 0.98,
    "sentiment": "Neutral",
    "signal": "Long Build-up",
    "build_side": "Put Side",
    "conflict": false,
    "timestamp": "2025-10-03 10:00:10"
  },
  {
    "symbol": "BHARTIARTL",
    "price": 1872.7,
    "previous_close": 1867.6,
    "price_change_pct": 0.27,
    "price_direction": "\u2191",
    "total_ce_oi": 16085,
    "total_pe_oi": 9021,
    "oi_change_pct": 0.74,
    "ce_oi_change_pct": 0.45,
    "pe_oi_change_pct": 1.27,
    "oi_direction": "\u2191",
    "pcr": 0.56,
    "sentiment": "Bullish",
    "signal": "Long Build-up",
    "build_side": "Balanced",
    "conflict": false,
    "timestamp": "2025-10-03 10:00:11"
  },
  {
    "symbol": "BAJFINANCE",
    "price": 979.3,
    "previous_close": 987.7,
    "price_change_pct": -0.85,
    "price_direction": "\u2193",
    "total_ce_oi": 19555,
    "total_pe_oi": 12756,
    "oi_change_pct": 1.02,
    "ce_oi_change_pct": 0.91,
    "pe_oi_change_pct": 1.18,
    "oi_direction": "\u2191",
    "pcr": 0.65,
    "sentiment": "Bullish",
    "signal": "Short Build-up \u26a0\ufe0f",
    "build_side": "Balanced",
    "conflict": true,
    "timestamp": "2025-10-03 10:00:11"
  },
  {
    "symbol": "SUNPHARMA",
    "price": 1631.8,
    "previous_close": 1636.2,
    "price_change_pct": -0.27,
    "price_direction": "\u2193",
    "total_ce_oi": 8444,
    "total_pe_oi": 10158,
    "oi_change_pct": -0.18,
    "ce_oi_change_pct": 0.29,
    "pe_oi_change_pct": -0.56,
    "oi_direction": "\u2193",
    "pcr": 1.2,
    "sentiment": "Neutral",
    "signal": "Long Unwinding",
    "build_side": "Balanced",
    "conflict": false,
    "timestamp": "2025-10-03 10:00:12"
  },
  {
    "symbol": "TECHM",
    "price": 1419.7,
    "previous_close": 1416.0,
    "price_change_pct": 0.26,
    "price_direction": "\u2191",
    "total_ce_oi": 5663,
    "total_pe_oi": 5219,
    "oi_change_pct": 1.06,
    "ce_oi_change_pct": 1.07,
    "pe_oi_change_pct": 1.05,
    "oi_direction": "\u2191",
    "pcr": 0.92,
    "sentiment": "Neutral",
    "signal": "Long Build-up",
    "build_side": "Balanced",
    "conflict": false,
    "timestamp": "2025-10-03 10:00:13"
  },
  {
    "symbol": "NTPC",
    "price": 340.5,
    "previous_close": 340.25,
    "price_change_pct": 0.07,
    "price_direction": "\u2191",
    "total_ce_oi": 11809,
    "total_pe_oi": 8636,
    "oi_change_pct": 0.42,
    "ce_oi_change_pct": 0.53,
    "pe_oi_change_pct": 0.27,
    "oi_direction": "\u2191",
    "pcr": 0.73,
    "sentiment": "Bullish",
    "signal": "Long Build-up",
    "build_side": "Balanced",
    "conflict": false,
    "timestamp": "2025-10-03 10:00:13"
  },
  {
    "symbol": "ONGC",
    "price": 240.6,
    "previous_close": 243.04,
    "price_change_pct": -1.0,
    "price_direction": "\u2193",
    "total_ce_oi": 12886,
    "total_pe_oi": 8000,
    "oi_change_pct": 0.45,
    "ce_oi_change_pct": 0.54,
    "pe_oi_change_pct": 0.3,
    "oi_direction": "\u2191",
    "pcr": 0.62,
    "sentiment": "Bullish",
    "signal": "Short Build-up \u26a0\ufe0f",
    "build_side": "Balanced",
    "conflict": true,
    "timestamp": "2025-10-03 10:00:14"
  },
  {
    "symbol": "TATAMOTORS",
    "price": 724.8,
    "previous_close": 718.35,
    "price_change_pct": 0.9,
    "price_direction": "\u2191",
    "total_ce_oi": 77254,
    "total_pe_oi": 53296,
    "oi_change_pct": 2.45,
    "ce_oi_change_pct": 4.04,
    "pe_oi_change_pct": 0.23,
    "oi_direction": "\u2191",
    "pcr": 0.69,
    "sentiment": "Bullish",
    "signal": "Long Build-up",
    "build_side": "Call Side",
    "conflict": false,
    "timestamp": "2025-10-03 10:00:15"
  },
  {
    "symbol": "BAJAJFINSV",
    "price": 1984.6,
    "previous_close": 2007.0,
    "price_change_pct": -1.12,
    "price_direction": "\u2193",
    "total_ce_oi": 4960,
    "total_pe_oi": 3803,
    "oi_change_pct": 3.17,
    "ce_oi_change_pct": 4.07,
    "pe_oi_change_pct": 2.01,
    "oi_direction": "\u2191",
    "pcr": 0.77,
    "sentiment": "Bullish",
    "signal": "Short Build-up \u26a0\ufe0f",
    "build_side": "Call Side",
    "conflict": true,
    "timestamp": "2025-10-03 10:00:16"
  },
  {
    "symbol": "HDFCLIFE",
    "price": 761.1,
    "previous_close": 764.0,
    "price_change_pct": -0.38,
    "price_direction": "\u2193",
    "total_ce_oi": 3867,
    "total_pe_oi": 3135,
    "oi_change_pct": 1.46,
    "ce_oi_change_pct": 2.68,
    "pe_oi_change_pct": 0.0,
    "oi_direction": "\u2191",
    "pcr": 0.81,
    "sentiment": "Neutral",
    "signal": "Short Build-up",
    "build_side": "Call Side",
    "conflict": false,
    "timestamp": "2025-10-03 10:00:16"
  },
  {
    "symbol": "ADANIENT",
    "price": 2597.5,
    "previous_close": 2592.7,
    "price_change_pct": 0.19,
    "price_direction": "\u2191",
    "total_ce_oi": 18094,
    "total_pe_oi": 11627,
    "oi_change_pct": 1.46,
    "ce_oi_change_pct": 1.55,
    "pe_oi_change_pct": 1.31,
    "oi_direction": "\u2191",
    "pcr": 0.64,
    "sentiment": "Bullish",
    "signal": "Long Build-up",
    "build_side": "Balanced",
    "conflict": false,
    "timestamp": "2025-10-03 10:00:17"
  },
  {
    "symbol": "DIVISLAB",
    "price": 5770.0,
    "previous_close": 5710.0,
    "price_change_pct": 1.05,
    "price_direction": "\u2191",
    "total_ce_oi": 6987,
    "total_pe_oi": 4419,
    "oi_change_pct": 0.79,
    "ce_oi_change_pct": 1.09,
    "pe_oi_change_pct": 0.32,
    "oi_direction": "\u2191",
    "pcr": 0.63,
    "sentiment": "Bullish",
    "signal": "Long Build-up",
    "build_side": "Balanced",
    "conflict": false,
    "timestamp": "2025-10-03 10:00:18"
  },
  {
    "symbol": "EICHERMOT",
    "price": 6870.0,
    "previous_close": 7021.5,
    "price_change_pct": -2.16,
    "price_direction": "\u2193",
    "total_ce_oi": 8571,
    "total_pe_oi": 6951,
    "oi_change_pct": 2.35,
    "ce_oi_change_pct": 2.76,
    "pe_oi_change_pct": 1.85,
    "oi_direction": "\u2191",
    "pcr": 0.81,
    "sentiment": "Neutral",
    "signal": "Short Build-up",
    "build_side": "Balanced",
    "conflict": false,
    "timestamp": "2025-10-03 10:00:18"
  },
  {
    "symbol": "M&M",
    "price": 3424.2,
    "previous_close": 3463.4,
    "price_change_pct": -1.13,
    "price_direction": "\u2193",
    "total_ce_oi": 20566,
    "total_pe_oi": 12947,
    "oi_change_pct": 1.88,
    "ce_oi_change_pct": 1.59,
    "pe_oi_change_pct": 2.36,
    "oi_direction": "\u2191",
    "pcr": 0.63,
    "sentiment": "Bullish",
    "signal": "Short Build-up \u26a0\ufe0f",
    "build_side": "Balanced",
    "conflict": true,
    "timestamp": "2025-10-03 10:00:19"
  },
  {
    "symbol": "COALINDIA",
    "price": 383.25,
    "previous_close": 388.5,
    "price_change_pct": -1.35,
    "price_direction": "\u2193",
    "total_ce_oi": 12952,
    "total_pe_oi": 10789,
    "oi_change_pct": 1.0,
    "ce_oi_change_pct": 0.72,
    "pe_oi_change_pct": 1.32,
    "oi_direction": "\u2191",
    "pcr": 0.83,
    "sentiment": "Neutral",
    "signal": "Short Build-up",
    "build_side": "Balanced",
    "conflict": false,
    "timestamp": "2025-10-03 10:00:20"
  },
  {
    "symbol": "JIOFIN",
    "price": 300.95,
    "previous_close": 300.05,
    "price_change_pct": 0.3,
    "price_direction": "\u2191",
    "total_ce_oi": 19241,
    "total_pe_oi": 14868,
    "oi_change_pct": 0.15,
    "ce_oi_change_pct": 0.19,
    "pe_oi_change_pct": 0.1,
    "oi_direction": "\u2191",
    "pcr": 0.77,
    "sentiment": "Bullish",
    "signal": "Long Build-up",
    "build_side": "Balanced",
    "conflict": false,
    "timestamp": "2025-10-03 10:00:20"
  },
  {
    "symbol": "IDFCFIRSTB",
    "price": 69.12,
    "previous_close": 69.02,
    "price_change_pct": 0.14,
    "price_direction": "\u2191",
    "total_ce_oi": 11064,
    "total_pe_oi": 6932,
    "oi_change_pct": 0.52,
    "ce_oi_change_pct": 0.54,
    "pe_oi_change_pct": 0.49,
    "oi_direction": "\u2191",
    "pcr": 0.63,
    "sentiment": "Bullish",
    "signal": "Long Build-up",
    "build_side": "Balanced",
    "conflict": false,
    "timestamp": "2025-10-03 10:00:21"
  },
  {
    "symbol": "BHEL",
    "price": 243.06,
    "previous_close": 240.17,
    "price_change_pct": 1.2,
    "price_direction": "\u2191",
    "total_ce_oi": 6229,
    "total_pe_oi": 4736,
    "oi_change_pct": 0.65,
    "ce_oi_change_pct": 0.6,
    "pe_oi_change_pct": 0.72,
    "oi_direction": "\u2191",
    "pcr": 0.76,
    "sentiment": "Bullish",
    "signal": "Long Build-up",
    "build_side": "Balanced",
    "conflict": false,
    "timestamp": "2025-10-03 10:00:22"
  },
  {
    "symbol": "BPCL",
    "price": 340.2,
    "previous_close": 339.7,
    "price_change_pct": 0.15,
    "price_direction": "\u2191",
    "total_ce_oi": 4856,
    "total_pe_oi": 3554,
    "oi_change_pct": 0.3,
    "ce_oi_change_pct": 0.62,
    "pe_oi_change_pct": -0.14,
    "oi_direction": "\u2191",
    "pcr": 0.73,
    "sentiment": "Bullish",
    "signal": "Long Build-up",
    "build_side": "Balanced",
    "conflict": false,
    "timestamp": "2025-10-03 10:00:22"
  },
  {
    "symbol": "DRREDDY",
    "price": 1251.8,
    "previous_close": 1244.7,
    "price_change_pct": 0.57,
    "price_direction": "\u2191",
    "total_ce_oi": 3862,
    "total_pe_oi": 3370,
    "oi_change_pct": 1.3,
    "ce_oi_change_pct": 0.57,
    "pe_oi_change_pct": 2.15,
    "oi_direction": "\u2191",
    "pcr": 0.87,
    "sentiment": "Neutral",
    "signal": "Long Build-up",
    "build_side": "Put Side",
    "conflict": false,
    "timestamp": "2025-10-03 10:00:23"
  }
]