[
  {
    "symbol": "RELIANCE",
    "price": 1381.9,
    "previous_close": 1386.2,
    "price_change_pct": -0.31,
    "price_direction": "\u2193",
    "total_ce_oi": 0,
    "total_pe_oi": 0,
    "oi_change_pct": -100.0,
    "ce_oi_change_pct": -100.0,
    "pe_oi_change_pct": -100.0,
    "oi_direction": "\u2193",
    "pcr": 0,
    "sentiment": "Bullish",
    "signal": "Long Unwinding",
    "build_side": "Balanced",
    "conflict": false,
    "timestamp": "2025-08-12 09:15:05"
  },
  {
    "symbol": "HDFCBANK",
    "price": 1984.9,
    "previous_close": 1995.6,
    "price_change_pct": -0.54,
    "price_direction": "\u2193",
    "total_ce_oi": 20905,
    "total_pe_oi": 0,
    "oi_change_pct": -62.97,
    "ce_oi_change_pct": -34.32,
    "pe_oi_change_pct": -100.0,
    "oi_direction": "\u2193",
    "pcr": 0.0,
    "sentiment": "Bullish",
    "signal": "Long Unwinding",
    "build_side": "Call Side",
    "conflict": false,
    "timestamp": "2025-08-12 09:15:10"
  },
  {
    "symbol": "LT",
    "price": 3680.0,
    "previous_close": 3668.4,
    "price_change_pct": 0.32,
    "price_direction": "\u2191",
    "total_ce_oi": 0,
    "total_pe_oi": 0,
    "oi_change_pct": -100.0,
    "ce_oi_change_pct": -100.0,
    "pe_oi_change_pct": -100.0,
    "oi_direction": "\u2193",
    "pcr": 0,
    "sentiment": "Bullish",
    "signal": "Short Covering \u26a0\ufe0f",
    "build_side": "Balanced",
    "conflict": true,
    "timestamp": "2025-08-12 09:15:13"
  },
  {
    "symbol": "ITC",
    "price": 418.1,
    "previous_close": 416.85,
    "price_change_pct": 0.3,
    "price_direction": "\u2191",
    "total_ce_oi": 0,
    "total_pe_oi": 0,
    "oi_change_pct": -100.0,
    "ce_oi_change_pct": -100.0,
    "pe_oi_change_pct": -100.0,
    "oi_direction": "\u2193",
    "pcr": 0,
    "sentiment": "Bullish",
    "signal": "Short Covering \u26a0\ufe0f",
    "build_side": "Balanced",
    "conflict": true,
    "timestamp": "2025-08-12 09:15:15"
  },
  {
    "symbol": "SBIN",
    "price": 823.1,
    "previous_close": 823.45,
    "price_change_pct": -0.04,
    "price_direction": "\u2193",
    "total_ce_oi": 0,
    "total_pe_oi": 0,
    "oi_change_pct": -100.0,
    "ce_oi_change_pct": -100.0,
    "pe_oi_change_pct": -100.0,
    "oi_direction": "\u2193",
    "pcr": 0,
    "sentiment": "Bullish",
    "signal": "Long Unwinding",
    "build_side": "Balanced",
    "conflict": false,
    "timestamp": "2025-08-12 09:15:17"
  },
  {
    "symbol": "AXISBANK",
    "price": 1072.2,
    "previous_close": 1073.3,
    "price_change_pct": -0.1,
    "price_direction": "\u2193",
    "total_ce_oi": 0,
    "total_pe_oi": 0,
    "oi_change_pct": -100.0,
    "ce_oi_change_pct": -100.0,
    "pe_oi_change_pct": -100.0,
    "oi_direction": "\u2193",
    "pcr": 0,
    "sentiment": "Bullish",
    "signal": "Long Unwinding",
    "build_side": "Balanced",
    "conflict": false,
    "timestamp": "2025-08-12 09:15:22"
  },
  {
    "symbol": "KOTAKBANK",
    "price": 1966.7,
    "previous_close": 1975.9,
    "price_change_pct": -0.47,
    "price_direction": "\u2193",
    "total_ce_oi": 0,
    "total_pe_oi": 0,
    "oi_change_pct": -100.0,
    "ce_oi_change_pct": -100.0,
    "pe_oi_change_pct": -100.0,
    "oi_direction": "\u2193",
    "pcr": 0,
    "sentiment": "Bullish",
    "signal": "Long Unwinding",
    "build_side": "Balanced",
    "conflict": false,
    "timestamp": "2025-08-12 09:15:24"
  },
  {
    "symbol": "BHARTIARTL",
    "price": 1857.2,
    "previous_close": 1857.4,
    "price_change_pct": -0.01,
    "price_direction": "\u2193",
    "total_ce_oi": 0,
    "total_pe_oi": 0,
    "oi_change_pct": -100.0,
    "ce_oi_change_pct": -100.0,
    "pe_oi_change_pct": -100.0,
    "oi_direction": "\u2193",
    "pcr": 0,
    "sentiment": "Bullish",
    "signal": "Long Unwinding",
    "build_side": "Balanced",
    "conflict": false,
    "timestamp": "2025-08-12 09:15:26"
  },
  {
    "symbol": "BAJFINANCE",
    "price": 878.3,
    "previous_close": 877.8,
    "price_change_pct": 0.06,
    "price_direction": "\u2191",
    "total_ce_oi": 0,
    "total_pe_oi": 0,
    "oi_change_pct": -100.0,
    "ce_oi_change_pct": -100.0,
    "pe_oi_change_pct": -100.0,
    "oi_direction": "\u2193",
    "pcr": 0,
    "sentiment": "Bullish",
    "signal": "Short Covering \u26a0\ufe0f",
    "build_side": "Balanced",
    "conflict": true,
    "timestamp": "2025-08-12 09:15:28"
  },
  {
    "symbol": "SUNPHARMA",
    "price": 1614.1,
    "previous_close": 1608.4,
    "price_change_pct": 0.35,
    "price_direction": "\u2191",
    "total_ce_oi": 0,
    "total_pe_oi": 0,
    "oi_change_pct": -100.0,
    "ce_oi_change_pct": -100.0,
    "pe_oi_change_pct": -100.0,
    "oi_direction": "\u2193",
    "pcr": 0,
    "sentiment": "Bullish",
    "signal": "Short Covering \u26a0\ufe0f",
    "build_side": "Balanced",
    "conflict": true,
    "timestamp": "2025-08-12 09:15:30"
  },
  {
    "symbol": "TECHM",
    "price": 1483.5,
    "previous_close": 1481.1,
    "price_change_pct": 0.16,
    "price_direction": "\u2191",
    "total_ce_oi": 0,
    "total_pe_oi": 0,
    "oi_change_pct": -100.0,
    "ce_oi_change_pct": -100.0,
    "pe_oi_change_pct": -100.0,
    "oi_direction": "\u2193",
    "pcr": 0,
    "sentiment": "Bullish",
    "signal": "Short Covering \u26a0\ufe0f",
    "build_side": "Balanced",
    "conflict": true,
    "timestamp": "2025-08-12 09:15:33"
  },
  {
    "symbol": "NTPC",
    "price": 337.1,
    "previous_close": 336.15,
    "price_change_pct": 0.28,
    "price_direction": "\u2191",
    "total_ce_oi": 0,
    "total_pe_oi": 0,
    "oi_change_pct": -100.0,
    "ce_oi_change_pct": -100.0,
    "pe_oi_change_pct": -100.0,
    "oi_direction": "\u2193",
    "pcr": 0,
    "sentiment": "Bullish",
    "signal": "Short Covering \u26a0\ufe0f",
    "build_side": "Balanced",
    "conflict": true,
    "timestamp": "2025-08-12 09:15:35"
  },
  {
    "symbol": "ONGC",
    "price": 234.25,
    "previous_close": 233.79,
    "price_change_pct": 0.2,
    "price_direction": "\u2191",
    "total_ce_oi": 0,
    "total_pe_oi": 0,
    "oi_change_pct": -100.0,
    "ce_oi_change_pct": -100.0,
    "pe_oi_change_pct": -100.0,
    "oi_direction": "\u2193",
    "pcr": 0,
    "sentiment": "Bullish",
    "signal": "Short Covering \u26a0\ufe0f",
    "build_side": "Balanced",
    "conflict": true,
    "timestamp": "2025-08-12 09:15:38"
  },
  {
    "symbol": "TATAMOTORS",
    "price": 653.75,
    "previous_close": 653.75,
    "price_change_pct": 0.0,
    "price_direction": "\u2193",
    "total_ce_oi": 0,
    "total_pe_oi": 0,
    "oi_change_pct": -100.0,
    "ce_oi_change_pct": -100.0,
    "pe_oi_change_pct": -100.0,
    "oi_direction": "\u2193",
    "pcr": 0,
    "sentiment": "Bullish",
    "signal": "Long Unwinding",
    "build_side": "Balanced",
    "conflict": false,
    "timestamp": "2025-08-12 09:15:42"
  },
  {
    "symbol": "BAJAJFINSV",
    "price": 1929.0,
    "previous_close": 1922.8,
    "price_change_pct": 0.32,
    "price_direction": "\u2191",
    "total_ce_oi": 12853,
    "total_pe_oi": 7932,
    "oi_change_pct": -2.68,
    "ce_oi_change_pct": -2.94,
    "pe_oi_change_pct": -2.27,
    "oi_direction": "\u2193",
    "pcr": 0.62,
    "sentiment": "Bullish",
    "signal": "Short Covering \u26a0\ufe0f",
    "build_side": "Balanced",
    "conflict": true,
    "timestamp": "2025-08-12 09:15:44"
  },
  {
    "symbol": "HDFCLIFE",
    "price": 765.65,
    "previous_close": 764.75,
    "price_change_pct": 0.12,
    "price_direction": "\u2191",
    "total_ce_oi": 0,
    "total_pe_oi": 0,
    "oi_change_pct": -100.0,
    "ce_oi_change_pct": -100.0,
    "pe_oi_change_pct": -100.0,
    "oi_direction": "\u2193",
    "pcr": 0,
    "sentiment": "Bullish",
    "signal": "Short Covering \u26a0\ufe0f",
    "build_side": "Balanced",
    "conflict": true,
    "timestamp": "2025-08-12 09:15:46"
  },
  {
    "symbol": "ADANIENT",
    "price": 2278.7,
    "previous_close": 2283.4,
    "price_change_pct": -0.21,
    "price_direction": "\u2193",
    "total_ce_oi": 0,
    "total_pe_oi": 0,
    "oi_change_pct": -100.0,
    "ce_oi_change_pct": -100.0,
    "pe_oi_change_pct": -100.0,
    "oi_direction": "\u2193",
    "pcr": 0,
    "sentiment": "Bullish",
    "signal": "Long Unwinding",
    "build_side": "Balanced",
    "conflict": false,
    "timestamp": "2025-08-12 09:15:49"
  },
  {
    "symbol": "DIVISLAB",
    "price": 5974.5,
    "previous_close": 5992.0,
    "price_change_pct": -0.29,
    "price_direction": "\u2193",
    "total_ce_oi": 18217,
    "total_pe_oi": 9960,
    "oi_change_pct": -1.05,
    "ce_oi_change_pct": -1.0,
    "pe_oi_change_pct": -1.13,
    "oi_direction": "\u2193",
    "pcr": 0.55,
    "sentiment": "Bullish",
    "signal": "Long Unwinding",
    "build_side": "Balanced",
    "conflict": false,
    "timestamp": "2025-08-12 09:15:51"
  },
  {
    "symbol": "EICHERMOT",
    "price": 5662.5,
    "previous_close": 5671.5,
    "price_change_pct": -0.16,
    "price_direction": "\u2193",
    "total_ce_oi": 0,
    "total_pe_oi": 0,
    "oi_change_pct": -100.0,
    "ce_oi_change_pct": -100.0,
    "pe_oi_change_pct": -100.0,
    "oi_direction": "\u2193",
    "pcr": 0,
    "sentiment": "Bullish",
    "signal": "Long Unwinding",
    "build_side": "Balanced",
    "conflict": false,
    "timestamp": "2025-08-12 09:15:53"
  },
  {
    "symbol": "M&M",
    "price": 3201.0,
    "previous_close": 3186.2,
    "price_change_pct": 0.46,
    "price_direction": "\u2191",
    "total_ce_oi": 9823,
    "total_pe_oi": 781,
    "oi_change_pct": -80.22,
    "ce_oi_change_pct": -70.27,
    "pe_oi_change_pct": -96.2,
    "oi_direction": "\u2193",
    "pcr": 0.08,
    "sentiment": "Bullish",
    "signal": "Short Covering \u26a0\ufe0f",
    "build_side": "Call Side",
    "conflict": true,
    "timestamp": "2025-08-12 09:15:57"
  },
  {
    "symbol": "COALINDIA",
    "price": 382.75,
    "previous_close": 382.5,
    "price_change_pct": 0.07,
    "price_direction": "\u2191",
    "total_ce_oi": 22403,
    "total_pe_oi": 16602,
    "oi_change_pct": -0.47,
    "ce_oi_change_pct": -0.52,
    "pe_oi_change_pct": -0.42,
    "oi_direction": "\u2193",
    "pcr": 0.74,
    "sentiment": "Bullish",
    "signal": "Short Covering \u26a0\ufe0f",
    "build_side": "Balanced",
    "conflict": true,
    "timestamp": "2025-08-12 09:15:59"
  },
  {
    "symbol": "JIOFIN",
    "price": 328.8,
    "previous_close": 327.75,
    "price_change_pct": 0.32,
    "price_direction": "\u2191",
    "total_ce_oi": 847,
    "total_pe_oi": 0,
    "oi_change_pct": -97.85,
    "ce_oi_change_pct": -96.43,
    "pe_oi_change_pct": -100.0,
    "oi_direction": "\u2193",
    "pcr": 0.0,
    "sentiment": "Bullish",
    "signal": "Short Covering \u26a0\ufe0f",
    "build_side": "Call Side",
    "conflict": true,
    "timestamp": "2025-08-12 09:16:03"
  },
  {
    "symbol": "IDFCFIRSTB",
    "price": 69.88,
    "previous_close": 69.68,
    "price_change_pct": 0.29,
    "price_direction": "\u2191",
    "total_ce_oi": 0,
    "total_pe_oi": 0,
    "oi_change_pct": -100.0,
    "ce_oi_change_pct": -100.0,
    "pe_oi_change_pct": -100.0,
    "oi_direction": "\u2193",
    "pcr": 0,
    "sentiment": "Bullish",
    "signal": "Short Covering \u26a0\ufe0f",
    "build_side": "Balanced",
    "conflict": true,
    "timestamp": "2025-08-12 09:16:06"
  },
  {
    "symbol": "BHEL",
    "price": 221.11,
    "previous_close": 221.46,
    "price_change_pct": -0.16,
    "price_direction": "\u2193",
    "total_ce_oi": 14806,
    "total_pe_oi": 8105,
    "oi_change_pct": -0.26,
    "ce_oi_change_pct": -0.25,
    "pe_oi_change_pct": -0.28,
    "oi_direction": "\u2193",
    "pcr": 0.55,
    "sentiment": "Bullish",
    "signal": "Long Unwinding",
    "build_side": "Balanced",
    "conflict": false,
    "timestamp": "2025-08-12 09:16:08"
  },
  {
    "symbol": "BPCL",
    "price": 321.1,
    "previous_close": 320.95,
    "price_change_pct": 0.05,
    "price_direction": "\u2191",
    "total_ce_oi": 8016,
    "total_pe_oi": 4672,
    "oi_change_pct": -1.44,
    "ce_oi_change_pct": -2.06,
    "pe_oi_change_pct": -0.36,
    "oi_direction": "\u2193",
    "pcr": 0.58,
    "sentiment": "Bullish",
    "signal": "Short Covering \u26a0\ufe0f",
    "build_side": "Put Side",
    "conflict": true,
    "timestamp": "2025-08-12 09:16:10"
  }
]