[
  {
    "symbol": "ITC",
    "price": 293.9,
    "previous_close": 294.85,
    "price_change_pct": -0.32,
    "price_direction": "\u2193",
    "total_ce_oi": 0,
    "total_pe_oi": 0,
    "oi_change_pct": 0.0,
    "ce_oi_change_pct": 0.0,
    "pe_oi_change_pct": 0.0,
    "oi_direction": "\u2193",
    "pcr": null,
    "sentiment": "Neutral",
    "signal": "Long Unwinding",
    "build_side": "Balanced",
    "conflict": false,
    "timestamp": "2026-04-07 09:45:04"
  },
  {
    "symbol": "SBIN",
    "price": 1021.4,
    "previous_close": 1032.75,
    "price_change_pct": -1.1,
    "price_direction": "\u2193",
    "total_ce_oi": 0,
    "total_pe_oi": 0,
    "oi_change_pct": 0.0,
    "ce_oi_change_pct": 0.0,
    "pe_oi_change_pct": 0.0,
    "oi_direction": "\u2193",
    "pcr": null,
    "sentiment": "Neutral",
    "signal": "Long Unwinding",
    "build_side": "Balanced",
    "conflict": false,
    "timestamp": "2026-04-07 09:45:04"
  },
  {
    "symbol": "TCS",
    "price": 2469.8,
    "previous_close": 2473.9,
    "price_change_pct": -0.17,
    "price_direction": "\u2193",
    "total_ce_oi": 0,
    "total_pe_oi": 0,
    "oi_change_pct": 0.0,
    "ce_oi_change_pct": 0.0,
    "pe_oi_change_pct": 0.0,
    "oi_direction": "\u2193",
    "pcr": null,
    "sentiment": "Neutral",
    "signal": "Long Unwinding",
    "build_side": "Balanced",
    "conflict": false,
    "timestamp": "2026-04-07 09:45:04"
  },
  {
    "symbol": "BHARTIARTL",
    "price": 1793.4,
    "previous_close": 1792.8,
    "price_change_pct": 0.03,
    "price_direction": "\u2191",
    "total_ce_oi": 0,
    "total_pe_oi": 0,
    "oi_change_pct": 0.0,
    "ce_oi_change_pct": 0.0,
    "pe_oi_change_pct": 0.0,
    "oi_direction": "\u2193",
    "pcr": null,
    "sentiment": "Neutral",
    "signal": "Short Covering",
    "build_side": "Balanced",
    "conflict": false,
    "timestamp": "2026-04-07 09:45:04"
  },
  {
    "symbol": "RELIANCE",
    "price": 1292.0,
    "previous_close": 1304.7,
    "price_change_pct": -0.97,
    "price_direction": "\u2193",
    "total_ce_oi": 0,
    "total_pe_oi": 0,
    "oi_change_pct": 0.0,
    "ce_oi_change_pct": 0.0,
    "pe_oi_change_pct": 0.0,
    "oi_direction": "\u2193",
    "pcr": null,
    "sentiment": "Neutral",
    "signal": "Long Unwinding",
    "build_side": "Balanced",
    "conflict": false,
    "timestamp": "2026-04-07 09:45:04"
  },
  {
    "symbol": "AXISBANK",
    "price": 1225.8,
    "previous_close": 1245.3,
    "price_change_pct": -1.57,
    "price_direction": "\u2193",
    "total_ce_oi": 0,
    "total_pe_oi": 0,
    "oi_change_pct": 0.0,
    "ce_oi_change_pct": 0.0,
    "pe_oi_change_pct": 0.0,
    "oi_direction": "\u2193",
    "pcr": null,
    "sentiment": "Neutral",
    "signal": "Long Unwinding",
    "build_side": "Balanced",
    "conflict": false,
    "timestamp": "2026-04-07 09:45:04"
  },
  {
    "symbol": "BAJFINANCE",
    "price": 856.8,
    "previous_close": 850.85,
    "price_change_pct": 0.7,
    "price_direction": "\u2191",
    "total_ce_oi": 0,
    "total_pe_oi": 0,
    "oi_change_pct": 0.0,
    "ce_oi_change_pct": 0.0,
    "pe_oi_change_pct": 0.0,
    "oi_direction": "\u2193",
    "pcr": null,
    "sentiment": "Neutral",
    "signal": "Short Covering",
    "build_side": "Balanced",
    "conflict": false,
    "timestamp": "2026-04-07 09:45:04"
  },
  {
    "symbol": "ICICIBANK",
    "price": 1218.9,
    "previous_close": 1231.4,
    "price_change_pct": -1.02,
    "price_direction": "\u2193",
    "total_ce_oi": 0,
    "total_pe_oi": 0,
    "oi_change_pct": 0.0,
    "ce_oi_change_pct": 0.0,
    "pe_oi_change_pct": 0.0,
    "oi_direction": "\u2193",
    "pcr": null,
    "sentiment": "Neutral",
    "signal": "Long Unwinding",
    "build_side": "Balanced",
    "conflict": false,
    "timestamp": "2026-04-07 09:45:04"
  },
  {
    "symbol": "HDFCBANK",
    "price": 763.5,
    "previous_close": 771.0,
    "price_change_pct": -0.97,
    "price_direction": "\u2193",
    "total_ce_oi": 0,
    "total_pe_oi": 0,
    "oi_change_pct": 0.0,
    "ce_oi_change_pct": 0.0,
    "pe_oi_change_pct": 0.0,
    "oi_direction": "\u2193",
    "pcr": null,
    "sentiment": "Neutral",
    "signal": "Long Unwinding",
    "build_side": "Balanced",
    "conflict": false,
    "timestamp": "2026-04-07 09:45:04"
  },
  {
    "symbol": "LT",
    "price": 3683.9,
    "previous_close": 3727.7,
    "price_change_pct": -1.17,
    "price_direction": "\u2193",
    "total_ce_oi": 0,
    "total_pe_oi": 0,
    "oi_change_pct": 0.0,
    "ce_oi_change_pct": 0.0,
    "pe_oi_change_pct": 0.0,
    "oi_direction": "\u2193",
    "pcr": null,
    "sentiment": "Neutral",
    "signal": "Long Unwinding",
    "build_side": "Balanced",
    "conflict": false,
    "timestamp": "2026-04-07 09:45:04"
  },
  {
    "symbol": "INFY",
    "price": 1301.4,
    "previous_close": 1306.2,
    "price_change_pct": -0.37,
    "price_direction": "\u2193",
    "total_ce_oi": 0,
    "total_pe_oi": 0,
    "oi_change_pct": 0.0,
    "ce_oi_change_pct": 0.0,
    "pe_oi_change_pct": 0.0,
    "oi_direction": "\u2193",
    "pcr": null,
    "sentiment": "Neutral",
    "signal": "Long Unwinding",
    "build_side": "Balanced",
    "conflict": false,
    "timestamp": "2026-04-07 09:45:04"
  },
  {
    "symbol": "KOTAKBANK",
    "price": 359.45,
    "previous_close": 360.55,
    "price_change_pct": -0.31,
    "price_direction": "\u2193",
    "total_ce_oi": 0,
    "total_pe_oi": 0,
    "oi_change_pct": 0.0,
    "ce_oi_change_pct": 0.0,
    "pe_oi_change_pct": 0.0,
    "oi_direction": "\u2193",
    "pcr": null,
    "sentiment": "Neutral",
    "signal": "Long Unwinding",
    "build_side": "Balanced",
    "conflict": false,
    "timestamp": "2026-04-07 09:45:05"
  },
  {
    "symbol": "SUNPHARMA",
    "price": 1701.4,
    "previous_close": 1694.6,
    "price_change_pct": 0.4,
    "price_direction": "\u2191",
    "total_ce_oi": 0,
    "total_pe_oi": 0,
    "oi_change_pct": 0.0,
    "ce_oi_change_pct": 0.0,
    "pe_oi_change_pct": 0.0,
    "oi_direction": "\u2193",
    "pcr": null,
    "sentiment": "Neutral",
    "signal": "Short Covering",
    "build_side": "Balanced",
    "conflict": false,
    "timestamp": "2026-04-07 09:45:05"
  },
  {
    "symbol": "TECHM",
    "price": 1455.2,
    "previous_close": 1449.5,
    "price_change_pct": 0.39,
    "price_direction": "\u2191",
    "total_ce_oi": 0,
    "total_pe_oi": 0,
    "oi_change_pct": 0.0,
    "ce_oi_change_pct": 0.0,
    "pe_oi_change_pct": 0.0,
    "oi_direction": "\u2193",
    "pcr": null,
    "sentiment": "Neutral",
    "signal": "Short Covering",
    "build_side": "Balanced",
    "conflict": false,
    "timestamp": "2026-04-07 09:45:05"
  },
  {
    "symbol": "ADANIENT",
    "price": 1880.4,
    "previous_close": 1902.2,
    "price_change_pct": -1.15,
    "price_direction": "\u2193",
    "total_ce_oi": 0,
    "total_pe_oi": 0,
    "oi_change_pct": 0.0,
    "ce_oi_change_pct": 0.0,
    "pe_oi_change_pct": 0.0,
    "oi_direction": "\u2193",
    "pcr": null,
    "sentiment": "Neutral",
    "signal": "Long Unwinding",
    "build_side": "Balanced",
    "conflict": false,
    "timestamp": "2026-04-07 09:45:05"
  },
  {
    "symbol": "NTPC",
    "price": 368.05,
    "previous_close": 366.1,
    "price_change_pct": 0.53,
    "price_direction": "\u2191",
    "total_ce_oi": 0,
    "total_pe_oi": 0,
    "oi_change_pct": 0.0,
    "ce_oi_change_pct": 0.0,
    "pe_oi_change_pct": 0.0,
    "oi_direction": "\u2193",
    "pcr": null,
    "sentiment": "Neutral",
    "signal": "Short Covering",
    "build_side": "Balanced",
    "conflict": false,
    "timestamp": "2026-04-07 09:45:05"
  },
  {
    "symbol": "ONGC",
    "price": 284.2,
    "previous_close": 281.85,
    "price_change_pct": 0.83,
    "price_direction": "\u2191",
    "total_ce_oi": 0,
    "total_pe_oi": 0,
    "oi_change_pct": 0.0,
    "ce_oi_change_pct": 0.0,
    "pe_oi_change_pct": 0.0,
    "oi_direction": "\u2193",
    "pcr": null,
    "sentiment": "Neutral",
    "signal": "Short Covering",
    "build_side": "Balanced",
    "conflict": false,
    "timestamp": "2026-04-07 09:45:05"
  },
  {
    "symbol": "BAJAJFINSV",
    "price": 1670.8,
    "previous_close": 1672.3,
    "price_change_pct": -0.09,
    "price_direction": "\u2193",
    "total_ce_oi": 0,
    "total_pe_oi": 0,
    "oi_change_pct": 0.0,
    "ce_oi_change_pct": 0.0,
    "pe_oi_change_pct": 0.0,
    "oi_direction": "\u2193",
    "pcr": null,
    "sentiment": "Neutral",
    "signal": "Long Unwinding",
    "build_side": "Balanced",
    "conflict": false,
    "timestamp": "2026-04-07 09:45:05"
  },
  {
    "symbol": "DIVISLAB",
    "price": 5775.0,
    "previous_close": 5821.0,
    "price_change_pct": -0.79,
    "price_direction": "\u2193",
    "total_ce_oi": 0,
    "total_pe_oi": 0,
    "oi_change_pct": 0.0,
    "ce_oi_change_pct": 0.0,
    "pe_oi_change_pct": 0.0,
    "oi_direction": "\u2193",
    "pcr": null,
    "sentiment": "Neutral",
    "signal": "Long Unwinding",
    "build_side": "Balanced",
    "conflict": false,
    "timestamp": "2026-04-07 09:45:05"
  },
  {
    "symbol": "HDFCLIFE",
    "price": 576.0,
    "previous_close": 580.4,
    "price_change_pct": -0.76,
    "price_direction": "\u2193",
    "total_ce_oi": 0,
    "total_pe_oi": 0,
    "oi_change_pct": 0.0,
    "ce_oi_change_pct": 0.0,
    "pe_oi_change_pct": 0.0,
    "oi_direction": "\u2193",
    "pcr": null,
    "sentiment": "Neutral",
    "signal": "Long Unwinding",
    "build_side": "Balanced",
    "conflict": false,
    "timestamp": "2026-04-07 09:45:06"
  },
  {
    "symbol": "M&M",
    "price": 2965.7,
    "previous_close": 3021.6,
    "price_change_pct": -1.85,
    "price_direction": "\u2193",
    "total_ce_oi": 0,
    "total_pe_oi": 0,
    "oi_change_pct": 0.0,
    "ce_oi_change_pct": 0.0,
    "pe_oi_change_pct": 0.0,
    "oi_direction": "\u2193",
    "pcr": null,
    "sentiment": "Neutral",
    "signal": "Long Unwinding",
    "build_side": "Balanced",
    "conflict": false,
    "timestamp": "2026-04-07 09:45:06"
  },
  {
    "symbol": "EICHERMOT",
    "price": 6467.0,
    "previous_close": 6596.0,
    "price_change_pct": -1.96,
    "price_direction": "\u2193",
    "total_ce_oi": 0,
    "total_pe_oi": 0,
    "oi_change_pct": 0.0,
    "ce_oi_change_pct": 0.0,
    "pe_oi_change_pct": 0.0,
    "oi_direction": "\u2193",
    "pcr": null,
    "sentiment": "Neutral",
    "signal": "Long Unwinding",
    "build_side": "Balanced",
    "conflict": false,
    "timestamp": "2026-04-07 09:45:06"
  },
  {
    "symbol": "COALINDIA",
    "price": 458.7,
    "previous_close": 459.55,
    "price_change_pct": -0.18,
    "price_direction": "\u2193",
    "total_ce_oi": 0,
    "total_pe_oi": 0,
    "oi_change_pct": 0.0,
    "ce_oi_change_pct": 0.0,
    "pe_oi_change_pct": 0.0,
    "oi_direction": "\u2193",
    "pcr": null,
    "sentiment": "Neutral",
    "signal": "Long Unwinding",
    "build_side": "Balanced",
    "conflict": false,
    "timestamp": "2026-04-07 09:45:06"
  },
  {
    "symbol": "JIOFIN",
    "price": 232.96,
    "previous_close": 235.31,
    "price_change_pct": -1.0,
    "price_direction": "\u2193",
    "total_ce_oi": 0,
    "total_pe_oi": 0,
    "oi_change_pct": 0.0,
    "ce_oi_change_pct": 0.0,
    "pe_oi_change_pct": 0.0,
    "oi_direction": "\u2193",
    "pcr": null,
    "sentiment": "Neutral",
    "signal": "Long Unwinding",
    "build_side": "Balanced",
    "conflict": false,
    "timestamp": "2026-04-07 09:45:06"
  },
  {
    "symbol": "DRREDDY",
    "price": 1202.3,
    "previous_close": 1217.8,
    "price_change_pct": -1.27,
    "price_direction": "\u2193",
    "total_ce_oi": 0,
    "total_pe_oi": 0,
    "oi_change_pct": 0.0,
    "ce_oi_change_pct": 0.0,
    "pe_oi_change_pct": 0.0,
    "oi_direction": "\u2193",
    "pcr": null,
    "sentiment": "Neutral",
    "signal": "Long Unwinding",
    "build_side": "Balanced",
    "conflict": false,
    "timestamp": "2026-04-07 09:45:07"
  },
  {
    "symbol": "IDFCFIRSTB",
    "price": 60.85,
    "previous_close": 61.08,
    "price_change_pct": -0.38,
    "price_direction": "\u2193",
    "total_ce_oi": 0,
    "total_pe_oi": 0,
    "oi_change_pct": 0.0,
    "ce_oi_change_pct": 0.0,
    "pe_oi_change_pct": 0.0,
    "oi_direction": "\u2193",
    "pcr": null,
    "sentiment": "Neutral",
    "signal": "Long Unwinding",
    "build_side": "Balanced",
    "conflict": false,
    "timestamp": "2026-04-07 09:45:07"
  },
  {
    "symbol": "BHEL",
    "price": 243.25,
    "previous_close": 245.64,
    "price_change_pct": -0.97,
    "price_direction": "\u2193",
    "total_ce_oi": 0,
    "total_pe_oi": 0,
    "oi_change_pct": 0.0,
    "ce_oi_change_pct": 0.0,
    "pe_oi_change_pct": 0.0,
    "oi_direction": "\u2193",
    "pcr": null,
    "sentiment": "Neutral",
    "signal": "Long Unwinding",
    "build_side": "Balanced",
    "conflict": false,
    "timestamp": "2026-04-07 09:45:07"
  },
  {
    "symbol": "BPCL",
    "price": 272.3,
    "previous_close": 278.7,
    "price_change_pct": -2.3,
    "price_direction": "\u2193",
    "total_ce_oi": 0,
    "total_pe_oi": 0,
    "oi_change_pct": 0.0,
    "ce_oi_change_pct": 0.0,
    "pe_oi_change_pct": 0.0,
    "oi_direction": "\u2193",
    "pcr": null,
    "sentiment": "Neutral",
    "signal": "Long Unwinding",
    "build_side": "Balanced",
    "conflict": false,
    "timestamp": "2026-04-07 09:45:07"
  }
]